{
	"mappings": {
		"jobs": {
			"properties": {
				"active": {
					"type": "boolean"
				},
				"id": {
					"type": "keyword"
				},
				"name": {
					"fields": {
						"search": {
							"analyzer": "folding_analyzer",
							"type": "text"
						}
					},
					"type": "keyword"
				},
				"parameters": {
					"type": "object"
				},
				"trainingFrequency": {
					"type": "keyword"
				},
				"trainingPeriod": {
					"type": "keyword"
				},
				"type": {
					"type": "keyword"
				}
			}
		}
	},
	"settings": {
		"analysis": {
			"analyzer": {
				"folding_analyzer": {
					"filter": [
						"asciifolding",
						"lowercase"
					],
					"tokenizer": "standard",
					"type": "custom"
				}
			}
		}
	}
}